ninjarmmpy/__init__.py
ninjarmmpy/auth.py
ninjarmmpy/client.py
ninjarmmpy/device.py
ninjarmmpy/groups.py
ninjarmmpy/management.py
ninjarmmpy/organization.py
ninjarmmpy/queries.py
ninjarmmpy/system.py
ninjarmmpy/utils.py
ninjarmmpy-0.2.1.dist-info/LICENSE
ninjarmmpy-0.2.1.dist-info/METADATA
ninjarmmpy-0.2.1.dist-info/WHEEL
ninjarmmpy-0.2.1.dist-info/top_level.txt
ninjarmmpy-0.2.1.dist-info/RECORD
