Metadata-Version: 2.1
Name: ninjarmmpy
Version: 0.2.1
Summary: Unofficial API client wrapper around v2 of the NinjaRMM API
Home-page: https://github.com/ak9999/ninjarmmpy
Author: Abdullah 'AJ' Khan
Author-email: aj@ajkhan.me
License: UNKNOWN
Platform: UNKNOWN
Classifier: Programming Language :: Python :: 3
Classifier: Operating System :: OS Independent
Requires-Python: >=3.7
Requires-Dist: requests (>=2.23.0)
